gaspard/__init__.py
gaspard/_modidx.py
gaspard/core.py
gaspard/toolloop.py
gaspard-0.0.1.dist-info/LICENSE
gaspard-0.0.1.dist-info/METADATA
gaspard-0.0.1.dist-info/WHEEL
gaspard-0.0.1.dist-info/entry_points.txt
gaspard-0.0.1.dist-info/top_level.txt
gaspard-0.0.1.dist-info/RECORD
