Metadata-Version: 2.1
Name: gaspard
Version: 0.0.1
Summary: Helper for Gemini API
Home-page: https://github.com/AnswerDotAI/gaspard
Author: Answer.AI
Author-email: info@fast.ai
License: Apache Software License 2.0
Keywords: nbdev jupyter notebook python
Classifier: Development Status :: 4 - Beta
Classifier: Intended Audience :: Developers
Classifier: Natural Language :: English
Classifier: Programming Language :: Python :: 3.9
Classifier: Programming Language :: Python :: 3.10
Classifier: Programming Language :: Python :: 3.11
Classifier: Programming Language :: Python :: 3.12
Classifier: License :: OSI Approved :: Apache Software License
Requires-Python: >=3.9
License-File: LICENSE
Requires-Dist: fastcore >=1.5.33
Requires-Dist: google-generativeai
Requires-Dist: toolslm >=0.0.7
Provides-Extra: dev
Requires-Dist: ipython ; extra == 'dev'
Requires-Dist: nbdev ; extra == 'dev'
